Metadata-Version: 2.1
Name: suz-distributions
Version: 0.1
Summary: Gaussian distributions
